odoo/addons/website_snippet_country_dropdown/README.rst
odoo/addons/website_snippet_country_dropdown/__init__.py
odoo/addons/website_snippet_country_dropdown/__manifest__.py
odoo/addons/website_snippet_country_dropdown/demo/pages.xml
odoo/addons/website_snippet_country_dropdown/i18n/es.po
odoo/addons/website_snippet_country_dropdown/i18n/fr.po
odoo/addons/website_snippet_country_dropdown/i18n/sl.po
odoo/addons/website_snippet_country_dropdown/i18n/website_snippet_country_dropdown.pot
odoo/addons/website_snippet_country_dropdown/readme/CONTRIBUTORS.rst
odoo/addons/website_snippet_country_dropdown/readme/DESCRIPTION.rst
odoo/addons/website_snippet_country_dropdown/readme/ROADMAP.rst
odoo/addons/website_snippet_country_dropdown/readme/USAGE.rst
odoo/addons/website_snippet_country_dropdown/static/description/icon.png
odoo/addons/website_snippet_country_dropdown/static/description/index.html
odoo/addons/website_snippet_country_dropdown/static/src/css/style.scss
odoo/addons/website_snippet_country_dropdown/static/src/js/web_tour_country_dropdown.js
odoo/addons/website_snippet_country_dropdown/static/src/js/website_snippet_country_dropdown.js
odoo/addons/website_snippet_country_dropdown/static/src/xml/country_dropdown.xml
odoo/addons/website_snippet_country_dropdown/templates/assets.xml
odoo/addons/website_snippet_country_dropdown/tests/__init__.py
odoo/addons/website_snippet_country_dropdown/tests/test_snippet_country_dropdown.py
odoo/addons/website_snippet_country_dropdown/views/snippets.xml
odoo13_addon_website_snippet_country_dropdown-13.0.1.0.1.dist-info/METADATA
odoo13_addon_website_snippet_country_dropdown-13.0.1.0.1.dist-info/WHEEL
odoo13_addon_website_snippet_country_dropdown-13.0.1.0.1.dist-info/top_level.txt
odoo13_addon_website_snippet_country_dropdown-13.0.1.0.1.dist-info/RECORD
